maleta/__init__.py
maleta-0.2.dist-info/METADATA
maleta-0.2.dist-info/WHEEL
maleta-0.2.dist-info/top_level.txt
maleta-0.2.dist-info/RECORD
